frasco_subdomains.py
setup.py
frasco_subdomains.egg-info/PKG-INFO
frasco_subdomains.egg-info/SOURCES.txt
frasco_subdomains.egg-info/dependency_links.txt
frasco_subdomains.egg-info/not-zip-safe
frasco_subdomains.egg-info/requires.txt
frasco_subdomains.egg-info/top_level.txt