Metadata-Version: 1.0
Name: frasco-subdomains
Version: 0.1
Summary: Subdomains awareness for Frasco
Home-page: http://github.com/frascoweb/frasco-subdomains
Author: Maxime Bouroumeau-Fuseau
Author-email: maxime.bouroumeau@gmail.com
License: MIT
Platform: any
